kaginawa/__init__.py
kaginawa/async_client.py
kaginawa/client.py
kaginawa/exceptions.py
kaginawa/models.py
kaginawa-0.0.8.dist-info/METADATA
kaginawa-0.0.8.dist-info/WHEEL
kaginawa-0.0.8.dist-info/top_level.txt
kaginawa-0.0.8.dist-info/RECORD
