Metadata-Version: 2.1
Name: kaginawa
Version: 0.0.8
Summary: *Unofficial* client for the Kagi API
Author-email: Estelle Poulin <dev@inspiredby.es>
License: GPLv3
Project-URL: homepage, https://github.com/estheruary/kaginawa
Project-URL: repository, https://github.com/estheruary/kaginawa
Project-URL: changelog, https://github.com/estheruary/kaginawa/-/blob/main/CHANGELOG.md
Keywords: kaginawa
Classifier: Programming Language :: Python :: 3
Requires-Python: >=3.9
Requires-Dist: httpx >=0.25.0
Provides-Extra: dev
Requires-Dist: black >=23 ; extra == 'dev'
Requires-Dist: flake8 >=6 ; extra == 'dev'
Requires-Dist: isort >=5 ; extra == 'dev'
Provides-Extra: test
Requires-Dist: pytest >=7 ; extra == 'test'
